<?xml version="1.0" encoding="utf-8"?>
<Product Title="Sony NEX-VG10" Type="Camcorder">
  <Features>
    <Feature Name="تاریخ معرفی ">2010/07/14</Feature>
    <Feature Name="نوع دوربین ">کارت حافظه ای Memory Card</Feature>
    <Feature Name="نوع ذخیره سازی ">کارت حافظه‌های Memory Stick PRO Duo / Pro-HG Duo / PRO-HG HX Duo - Media SD, SDHC and SDXC Memory Card</Feature>
    <Feature Name="ابعاد ">ابعاد بدنه 85 × 130 × 223 میلی‌متر و ابعاد دوربین با لنز همراه 97 × 132 × 294 میلی‌متر mm</Feature>
    <Feature Name="وزن ">به همراه لنز و لوازم 1300 گرم</Feature>
    <Feature Name="رنگ ">مشکی</Feature>
    <Feature Name="ساخت ">ژاپن</Feature>
    <Feature Name="نوع حسگر ">Exmor R CMOS</Feature>
    <Feature Name="دقت حسگر ">14.2 مگاپیکسل</Feature>
    <Feature Name="دقت مؤثر حسگر ">14.2 مگاپیکسل</Feature>
    <Feature Name="ابعاد حسگر ">15.6 × 23.4 میلی‌متر اینچ</Feature>
    <Feature Name="تنظیم سفیدی ">اتوماتیک، 2 حالت دستی، دمای رنگ/فیلتر (9900-2500 K) و حالت‌های نور روز _ سایه _ ابری _ تنگستن _ فلورسنت _ فلاش</Feature>
    <Feature Name="کیفیت فیلم ">Full HD</Feature>
    <Feature Name="فرمت فیلم ">(MPEG-4 AVC (H.264</Feature>
    <Feature Name="صدا ">دالبی دیجیتال AC-3 و Mpeg 4 AAC-LC</Feature>
    <Feature Name="قابلیت عکسبرداری ">بلی</Feature>
    <Feature Name="حداکثر سرعت شاتر ">1/4000 ثانیه</Feature>
    <Feature Name="حداقل سرعت شاتر ">1/4 ثانیه</Feature>
    <Feature Name="حالت های تصویر برداری ">دستیاتوماتیکالویت دیافراگمالویت شاترضد تارشدگیفیلم‌برداری بدون سه پایهسپیده‌دم</Feature>
    <Feature Name="شرکت سازنده لنز ">سونی</Feature>
    <Feature Name="فاصله کانونی ">18-200 میلیمتر</Feature>
    <Feature Name="بزرگنمایی اپتیکال ">11 برابر</Feature>
    <Feature Name="لرزشگیر تصویر ">بلی</Feature>
    <Feature Name="توضیحات لرزشگیر تصویر ">اپتیکال بر روی لنز انتخابی (Optical SteadyShot System On Selected Lenses)</Feature>
    <Feature Name="سایز فیلتر ">67 میلیمتر</Feature>
    <Feature Name="فوکوس دستی ">بلی</Feature>
    <Feature Name="فوکوس اتوماتیک ">بلی</Feature>
    <Feature Name="نوع صفحه نمایش ">صفحه نمایش لمسی و چرخان</Feature>
    <Feature Name="سایز صفحه نمایش ">3.0 اینچ</Feature>
    <Feature Name="دقت صفحه نمایش ">921,000 پیکسل</Feature>
    <Feature Name="چشمی ">بلی</Feature>
    <Feature Name="مشخصات چشمی ">چشمی الکترونیک 0.43 اینچی با کیفیت 921.000 نقطه</Feature>
    <Feature Name="ورودی میکروفون ">بلی</Feature>
    <Feature Name="ورودی Svideo ">خیر</Feature>
    <Feature Name="خروجی هدفون ">بلی</Feature>
    <Feature Name="خروجی HDMI ">بلی</Feature>
    <Feature Name="خروجی USB ">بلی</Feature>
    <Feature Name="خروجی تلویزیون ">بلی</Feature>
    <Feature Name="فلاش ">خیر</Feature>
    <Feature Name="فیلمبرداری در شب ">بلی</Feature>
    <Feature Name="حداقل نور ">11 لوکس</Feature>
    <Feature Name="کارت حافظه ">Memory Stick Pro Duo</Feature>
    <Feature Name="میکروفون داخلی ">بلی</Feature>
    <Feature Name="بلندگوی داخلی ">بلی</Feature>
    <Feature Name="باتری ">NP-FV70 باتری لیتیوم قابل شارژ مدل</Feature>
    <Feature Name="شارژر باتری ">بلی</Feature>
    <Feature Name="ریموت کنترل ">خیر</Feature>
    <Feature Name="سایر مشخصات ">دوربین فیلمبرداری با قابلیت تعویض لنزقابلیت ثاپورت لنز‌های Sony E-mount / Sony Alpha Lenses, Minolta and Konica Minolta AF Lenses Via Adaptor MF Only, Exclude Power Zoom Lenses/Tele-Convertersبه همراه یک لنز 200-18 میلی‌متری E-mount</Feature>
    <Feature Name="اقلام همراه دوربین ">لنز 200-18 میلی‌متری E-mountباتری لیتیوم قابل شارژ مدل NP-FV70شارژر باتریکابل شارژرکابل تلویزیونکابل USBدفترچه راهنماسی دی نرم افزاری</Feature>
  </Features>
  <Review ID="ReviewBody" Value="+1">
    <Sentence ID="rev-1" Value="+2">همانطور که گفتیم دوربین NEX-VG10 مجهز به سنسور 23.4 x 15.6 میلی متری 14.2 مگاپیکسلی موثر Exmor APS HD CMOS می باشد که با کیفیت‌ترین سنسور تصویر سونی است.</Sentence>
    <Sentence ID="rev-2" Value="0">ضبط ویدیویی Full HD می تواند در کیفیت های 24mbps و 16mbps انجام گیرد.</Sentence>
    <Sentence ID="rev-3" Value="0">فیلم برداری 1440 x 1080p در فرمت MPEG4 و کیفیت 9mbps نیز می تواند انجام شود.</Sentence>
    <Sentence ID="rev-4" Value="+2">یکی از نقاط قوت این دوربین توانایی ضبط صدای Dolby digital بسیار با کیفیت با کمک چهار میکروفون است.</Sentence>
    <Sentence ID="rev-5" Value="+2">بعلاوه توانایی بسیار عالی را نیز در حذف نویز پس زمینه دارد.</Sentence>
    <Sentence ID="rev-6" Value="0">یک جک میکروفون اکسترنال نیز بر روی این دوربین وجود دارد.</Sentence>
    <Sentence ID="rev-7" Value="+1">همانند دوربین های DSLR،  سنسور این دوربین فیلم برداری نیز از امکانات ضد گرد و غبار بهره می‌برد.</Sentence>
    <Sentence ID="rev-8" Value="+1">با استفاده از فن آوری لرزش فراصوت فیلتر سنسور غبار احتمالی نشسته بر روی آن برطرف می شود.</Sentence>
    <Sentence ID="rev-9" Value="0">این غبار ممکن است به هنگام تعویض لنز بر روی سنسور بنشیند.</Sentence>
    <Sentence ID="rev-10" Value="0">هنگام خرید این لنز با کیت لنز E18-200mm F3.5-6.3 OSS به فروش می رسد.</Sentence>
    <Sentence ID="rev-11" Value="+2">این لنز مجهز به لرزش گیر تصویر اپتیکال و سیستم فوکوس خودکار بسیار کم صدا می باشد.</Sentence>
    <Sentence ID="rev-12" Value="+2">در ضمن حالت واید بسیار عالی و بزرگنمایی 11X را نیز ارایه می کند.</Sentence>
    <Sentence ID="rev-13" Value="+1">بعلاوه قابلیت سازگاری با دیگر لنزهای E mount سونی را دارد.</Sentence>
    <Sentence ID="rev-14" Value="+1">با دیگر لنزهای Sony Alpha،  Minolta و Konica Minolta با آداپتور قابلیت سازگاری دارد.</Sentence>
    <Sentence ID="rev-15" Value="-1">البته با این لنزها دیگر فوکوس خودکار امکان‌پذیر نمی‌باشد.</Sentence>
    <Sentence ID="rev-16" Value="0">شوتینگ مودهای کامل یک دوربین DSLR مثل manual،  Shutter priority و Aperture priority نیز بر روی NEX-VG10 یافت می شوند.</Sentence>
    <Sentence ID="rev-17" Value="0">حساسیت سنسور یا ISO این دوربین از 200 تا 12800 قابل تنظیم است.</Sentence>
    <Sentence ID="rev-18" Value="0">برای حرفه ای ترها نیز باید بگوییم که سیستم نورسنجی این دوربین Multi-segment،  Center-weighted و Spot که بسیار شبیه به DSLR ها است عمل می کند.</Sentence>
    <Sentence ID="rev-19" Value="0">جبران نوردهی نیز تا 2EV عمل می کند.</Sentence>
    <Sentence ID="rev-20" Value="0">سرعت شاتر این دوربین در هنگام فیلم برداری از 1/4 ثانیه تا 1/4000 و در هنگام ضبط عکاسی از 30 ثانیه تا 1/4000 ثانیه می باشد.</Sentence>
    <Sentence ID="rev-21" Value="0">بهترین مقدار نور محیط برای فیلم برداری با این دوربین 11 لوکس می باشد تا فیلم های با کیفیت تری بدست آید.</Sentence>
    <Sentence ID="rev-22" Value="+2">این دوربین مجهز به چشمی الکترونیکی بسیار با کیفیت 0.43" XtraFine TruBlack با کیفیت 921,000 نقطه می باشد.</Sentence>
    <Sentence ID="rev-23" Value="+2">نمایشگر 3 اینچی بسیار با کیفیت XtraFine TruBlack نیز کیفیت 921,000 نقطه را ارایه می کند.</Sentence>
    <Sentence ID="rev-24" Value="0">این دوربین فلاش داخلی ندارد ولی فلاش اکسترنال به آن متصل می شود که اتفاقا به هنگام خرید در جعبه موجود است.</Sentence>
    <Sentence ID="rev-25" Value="0">از پورت های خروجی و ورودی می توان به خروجی HDMI برای اتصال به HDTV،  USB 2.0،  خروجی ویدیو NTSC/PAL،  جک هدفون استریو،  جک میکروفون استریو اکسترنال و ورودی DC اشاره کرد.</Sentence>
    <Sentence ID="rev-26" Value="+1">این دوربین از کارت های حافظه ی Memory Stick Pro Duo, Pro-HG Duo،  SD/SDHC و SDXC پشتیبانی می‌کند.</Sentence>
    <Sentence ID="rev-27" Value="0">یک باتری قابل شارژ لیتیوم-یونی 1650mAh نیز به همراه آن موجود می باشد.</Sentence>
    <Sentence ID="rev-28" Value="0">طبق ادعای شرکت این باتری با یک بار شارژ توانایی شارژدهی به مدت 330 دقیقه برای فیلم برداری را دارد.</Sentence>
    <Sentence ID="rev-29" Value="0">وزن کلی این دوربین 1.3 کیلوگرم می باشد.</Sentence>
    <Sentence ID="rev-30" Value="+1">در کل این دوربین را به افرادی که به فیلم برداری جدی و فیلم سازی آماتوری علاقه دارند پیشنهاد می کنیم.</Sentence>
  </Review>
  <General_Reviews>
    <General_Review ID="gr-1" Holder="مجتبي گلدوز " Value="+1">
      <Sentence ID="gr-1-1" Value="+1">دوربيني مناسب کار هاي معمولي است</Sentence>
    </General_Review>
    <General_Review ID="gr-2" Holder="ميهمان " Value="-2">
      <Sentence ID="gr-2-1" Value="0">با عرض سلام به تمامي دوستان اينجانب به مدت بيست سال است که تقريبا اکثر دوربينهاي تصوير برداري خانگي و حرفه اي را داشته و تست کرده ام .</Sentence>
      <Sentence ID="gr-2-2" Value="-1">متأسفانه ما انسانها خيلي زود با تبليغات گول ميخوريم و هنوز کالايي را نخريده در باره ان نظر ميدهيم .</Sentence>
      <Sentence ID="gr-2-3" Value="-1">دوستان من يک ماه قبل اين دوربين را خريدم و بعد از دو روز ان را با ضرر فروختم .</Sentence>
      <Sentence ID="gr-2-4" Value="-2">اولا: تصوير برداري با ان بسيار سخت ميباشد به دليل نداشتن دکمه تله وايد روي دستگاه و سفت بودن رينگ زوم روي لنز اورجينال که چرخاندن ان و تله وايد کردن باعث تکان خوردن دوربين شده و تصوير را خراب ميکند و در ضمن صداي ان هم درتصوير ضبط ميشود.</Sentence>
      <Sentence ID="gr-2-5" Value="-2">دوما :نورگيري ان بسيار کم است و در شرايط نور کم تصوير بسيار بي کيفيت ميشود.</Sentence>
      <Sentence ID="gr-2-6" Value="0">سوما :تصوير فيلمبرداري شده در تمام شرايط تصويربرداري به اصطلاح عامي فريم فريم است همانند دوربين گوشيهاي موبايل.</Sentence>
      <Sentence ID="gr-2-7" Value="-1">چهارما:بزرگ شدن سنسور سيموس هيچ چيز برتري را در کيفيت تصوير به جز کمي تاثير در عمق ميدان به جا نگذاشته که انچنان محسوس نيست و ان چه شما در تصور خود ناشي از تبليقات داريد نيست.</Sentence>
      <Sentence ID="gr-2-8" Value="-1">در مجموع من به اين دوربين بيشتر از 3 امتياز از 10 نميدهم و به نظر من اصلا ارزش اين قيمت را ندارد و با اين قيمت شما دوربينهاي بهتري ميتوانيد بخريد.</Sentence>
    </General_Review>
    <General_Review ID="gr-3" Holder="ميهمان " Value="-1">
      <Sentence ID="gr-3-1" Value="0">آنطور که در اينترنت مشخص است،  قيمت اين دوربين 2000 دلار يا حدود 2 ميليون تومان است.</Sentence>
      <Sentence ID="gr-3-2" Value="-1">اين دوربين به هر حال يک هندي کم است و قيمت دو ميليون تومان براي آن کمي زياد است.</Sentence>
    </General_Review>
    <General_Review ID="gr-4" Holder="ميهمان " Value="+1">
      <Sentence ID="gr-4-1" Value="+1">ظاهرا دوربين خوبي است  اگه بشه براي مراسمات ازش استفاده کرد که عالي ميشد</Sentence>
    </General_Review>
    <General_Review ID="gr-5" Holder="ميهمان " Value="+2">
      <Sentence ID="gr-5-1" Value="+2">يکي از زيباترين و حرفه‌اي ترين  و از همه مهمتر خوشگلترين دوربينهايي است که تابحال ديدم.</Sentence>
    </General_Review>
    <General_Review ID="gr-6" Holder="رضا " Value="+1">
      <Sentence ID="gr-6-1" Value="0">اين نخستين دوربين فيلم برداري HD از اين خانواده است که مي توانيد روي آن از لنزهاي مختلف استفاده کنيد.</Sentence>
      <Sentence ID="gr-6-2" Value="+2">علاقمندان به فيلم برداري حالا مي توانند به راحتي تصاوير تمام HD کاملا سينمايي و با کيفيت صداي فوق العاده داشته باشند.</Sentence>
      <Sentence ID="gr-6-3" Value="0">‏اين دوربين مي تواند از لنزهاي سري E‪-‬mount مخصوص فيلم برداري استفاده کند.</Sentence>
      <Sentence ID="gr-6-4" Value="0">همچنين مي تواند از لنزهاي مختلفي از سري A‪-‬mount که براي دوربين هاي DSLR سوني ارايه شده اند،  با يک اداپتور هماهنگ کننده استفاده کند.</Sentence>
      <Sentence ID="gr-6-5" Value="+1">در کنار اينها مي تواند از لنزهاي G سوني و لنزهاي کارل زايس هم بهره ببرد.</Sentence>
      <Sentence ID="gr-6-6" Value="0">‏ در واقع اين دوربين از فناوري مشابه Micro Four Thirds استفاده مي کند اما از آنجايي که اين فناوري به نام شرکت پاناسونيک و المپوس است،  شرکت سوني تصميم گرفته که فناوري خودش را Interchangeable Lens HD camcorder بنامد.</Sentence>
      <Sentence ID="gr-6-7" Value="0">ضمن اينکه اين نخستين هندي کم اي است که سنسور Exmor APS HD CMOS دارد.</Sentence>
      <Sentence ID="gr-6-8" Value="0">اين سنسور تقريبا ۱۹.</Sentence>
      <Sentence ID="gr-6-9" Value="0">۵ برابر بزرگ تر از سنسورهايي است که در دوربين هاي فيلم برداري معمول به کار رفته است.</Sentence>
      <Sentence ID="gr-6-10" Value="+2">و اين قدرت را دارد که عمق تصوير فوق العاده اي را به فيلم بردار ارايه دهد.</Sentence>
      <Sentence ID="gr-6-11" Value="0">اين دوربين همچنين مي تواند با کيفيت ۱۴ مگاپيکسل عکس برداري کند.</Sentence>
      <Sentence ID="gr-6-12" Value="+1">بنابراين کاربران مي توانند لذت عکاسي با کيفيت DSLR را با امکاناتي مانند Auto HDR تجربه کنند.</Sentence>
      <Sentence ID="gr-6-13" Value="0">دوربين NEX‪-‬VG10 با رزولوشن ۱۹۲۰ در ۱۰۸۰ با سرعت ۲۴ مگابيت در ثانيه فيلم برداري مي کند و به همراه يک لنز E‪-‬mount از نوع 18‪-‬200mm با زوم اپتيکال ۱۱ برابر ارايه مي شود.</Sentence>
      <Sentence ID="gr-6-14" Value="+2">‏سيستم صدا برداري دوربين جديد استريو است و با چهار ميکروفون مجزا صدا را از محيط با کيفيت عالي ثبت مي کند.</Sentence>
      <Sentence ID="gr-6-15" Value="0">در صورت تمايل مي توانيد ميکروفون عقب دوربين را خاموش کنيد تا صداي پس زمينه را کمتر کنيد.</Sentence>
      <Sentence ID="gr-6-16" Value="0">اين دوربين از ماه سپتامر با قيمتي حدود ۲۰۰۰ دلار ارايه خواهد شد</Sentence>
    </General_Review>
  </General_Reviews>
  <Critical_Reviews>
    <Critical_Review ID="cr-1" Holder="ميهمان" Score="36" Voters="60" Value="0">
      <Sentence ID="cr-1-1" Value="0">خريدار ميمونه دوربين حرفه اي عکاسي  با قابليت فيلمبرداري بخره يا دوربين حرفه اي فيلمبرداري  با قابليت عکاسي ؟</Sentence>
    </Critical_Review>
    <Critical_Review ID="cr-2" Holder="ميهمان" Score="18" Voters="52" Value="-2">
      <Sentence ID="cr-2-1" Value="0">با عرض سلام به تمامي دوستان اينجانب به مدت بيست سال است که تقريبا اکثر دوربينهاي تصوير برداري خانگي و حرفه اي را داشته و تست کرده ام .</Sentence>
      <Sentence ID="cr-2-2" Value="-1">متاسفانه ما انسانها خيلي زود با تبليغات گول ميخوريم وهنوز کالايي را نخريده در باره ان نظر ميدهيم .</Sentence>
      <Sentence ID="cr-2-3" Value="-1">دوستان من يک ماه قبل اين دوربين را خريدم و بعد از دو روز ان را با ضرر فروختم .</Sentence>
      <Sentence ID="cr-2-4" Value="-2">اولا: تصوير برداري با ان بسيار سخت ميباشد به دليل نداشتن دکمه تله وايد روي دستگاه و سفت بودن رينگ زوم روي لنز اورجينال که چرخاندن ان و تله وايد کردن باعث تکان خوردن دوربين شده و تصوير را خراب ميکند و در ضمن صداي ان هم درتصوير ضبط ميشود.</Sentence>
      <Sentence ID="cr-2-5" Value="-2">دوما :نورگيري ان بسيار کم است ودر شرايط نور کم تصوير بسيار بي کيفيت ميشود.</Sentence>
      <Sentence ID="cr-2-6" Value="0">سوما :تصوير فيلمبرداري شده در تمام شرايط تصويربرداري به اصطلاح عامي فريم فريم است همانند دوربين گوشيهاي موبايل.</Sentence>
      <Sentence ID="cr-2-7" Value="-1">چهارما:بزرگ شدن سنسور سيموس هيچ چيز برتري را در کيفيت تصوير به جز کمي تاثير در عمق ميدان به جا نگذاشته که انچنان محسوس نيست و ان چه شما در تصور خود ناشي از تبليقات داريد نيست.</Sentence>
      <Sentence ID="cr-2-8" Value="-1">در مجمو ع من به اين دوربين بيشتر از 3 امتياز از 10 نميدهم و به نظر من اصلا ارزش اين قيمت را ندارد و با اين قيمت شما دوربينهاي بهتري ميتوانيد بخريد.</Sentence>
    </Critical_Review>
    <Critical_Review ID="cr-3" Holder="ميهمان" Score="10" Voters="16" Value="+2">
      <Sentence ID="cr-3-1" Value="+2">واقعاً شاهکاره،  امکان فوکوس مشابه دوربين هاي عکاسي SLR ،  سنسور CMOS بزرگ،  رزولوشن بسيار بالا و ضبط تا 60 فريم بر ثانيه،  حجم و وزن کم يعني يک دوربين تقريبا حرفه اي در دست همه.</Sentence>
      <Sentence ID="cr-3-2" Value="0">من منتظرم بياد يکي ميخوام.</Sentence>
    </Critical_Review>
    <Critical_Review ID="cr-4" Holder="مهدي عبدي" Score="7" Voters="19" Value="+1">
      <Sentence ID="cr-4-1" Value="+1">بالاخره سوني تصميم گرفت در جشن 25 سالگي دوربين هاي هندي کم خود يکي از بهترين محصولات ساخته شده خود را وارد بازار کند يعني دوربين SONY NEX VG10 دوربيني که مخصوص خلق شاهکارهاي سينمايي مي باشد و در سپتامبر امسال با قيمت 2000 به بازار جهاني عرضه مي شود.</Sentence>
      <Sentence ID="cr-4-2" Value="+1">با تشکر از ديجي کالا</Sentence>
    </Critical_Review>
    <Critical_Review ID="cr-5" Holder="ميهمان" Score="3" Voters="5" Value="+2">
      <Sentence ID="cr-5-1" Value="+2">ايده آل ترين دوربين حال حاضر بازار  در رنج 2 ميليون تومان کيفيت فوق العاده باور نکردني که جناب آقاي مهندس حامد صلاحي نمونه فيلمبرداري ون رو در سايت شخصيشون قرار دادن لطفاٌ زير بار قيمت هايي که شرکت ها دارن مي دن نرين چون تا يکي دو ماه آينده با ورود انبوه به بازار قيمت ها شکسته خواهد شد </Sentence>
    </Critical_Review>
    <Critical_Review ID="cr-6" Holder="ميهمان" Score="4" Voters="6" Value="+2">
      <Sentence ID="cr-6-1" Value="+2">سلام دوستان خوب هستين به نظر من دوربين واقعاً جالب و خوش دستيه که هم کارايى بيشتر هم با اون کيفيت hd  يش رو دست هندى کم هاى دوى کم هم دوربين هاى دوى کم اومده هم سبک هم با کيفيت بيشتر از لنزش خوشم اومده که ميتونم عوضشم کنيم ابن کارايش به نظر من از همش مهمتره هم دقت 14 مکا بيکسليش </Sentence>
    </Critical_Review>
    <Critical_Review ID="cr-7" Holder="ميهمان" Score="11" Voters="35" Value="+2">
      <Sentence ID="cr-7-1" Value="+2">زيباترين و خوش‌دست ترين و چابک‌ترين و جذاب ترين و ..</Sentence>
      <Sentence ID="cr-7-2" Value="0">ترين دوربينيه که به عمرم ديدم.</Sentence>
    </Critical_Review>
  </Critical_Reviews>
  <Voters Value="18" />
  <Performance Value="8.50" />
  <Capability Value="8.50" />
  <Production_Quality Value="8.50" />
  <Ergonomics Value="8.50" />
  <Purchase_Value Value="8.50" />
  <Tags>
    <Tag Type="Target(M)" ID="elementID1000" Root="سنسور" Relation="review" />
    <Tag Type="Target(M)" ID="elementID1003" Root="ضبط صدا" Relation="review" />
    <Tag Type="Target(M)" ID="elementID1006" Root="چشمی الکترونیکی" Relation="review" />
    <Tag Type="Target(M)" ID="elementID1009" Root="نمایشگر" Relation="review" />
    <Tag Type="Target(M)" ID="elementID10012" Root="دوربين" Relation="gr-1" />
    <Tag Type="Target(M)" ID="elementID10015" Root="تصوير برداري" Relation="gr-2" />
    <Tag Type="Target(M)" ID="elementID10018" Root="رينگ زوم" Relation="gr-2" />
    <Tag Type="Target(M)" ID="elementID10021" Root="نورگيري" Relation="gr-2" />
    <Tag Type="Target(M)" ID="elementID10024" Root="تصوير" Relation="gr-2" />
    <Tag Type="Target(M)" ID="elementID10027" Root="ارزش" Relation="gr-2" />
    <Tag Type="Target(M)" ID="elementID10030" Root="قيمت" Relation="gr-3" />
    <Tag Type="Target(M)" ID="elementID10033" Root="دوربين" Relation="gr-4" />
    <Tag Type="Target(M)" ID="elementID10036" Root="دوربین" Relation="gr-5" />
    <Tag Type="Target(M)" ID="elementID10041" Root="کيفيت صدا" Relation="gr-6" />
    <Tag Type="Target(M)" ID="elementID10044" Root="عمق تصوير" Relation="gr-6" />
    <Tag Type="Target(M)" ID="elementID10047" Root="عکاسي" Relation="gr-6" />
    <Tag Type="Target(M)" ID="elementID10052" Root="رزولوشن" Relation="cr-3" />
    <Tag Type="Target(M)" ID="elementID10055" Root="حجم" Relation="cr-3" />
    <Tag Type="Target(M)" ID="elementID10058" Root="وزن" Relation="cr-3" />
    <Tag Type="Target(M)" ID="elementID10061" Root="دوربين" Relation="cr-5" />
    <Tag Type="Target(M)" ID="elementID10064" Root="کيفيت" Relation="cr-5" />
    <Tag Type="Target(M)" ID="elementID10067" Root="دوربين" Relation="cr-6" />
    <Tag Type="Target(M)" ID="elementID10071" Root="کارايى" Relation="cr-6" />
    <Tag Type="Target(M)" ID="elementID10074" Root="کيفيت" Relation="cr-6" />
    <Tag Type="Target(M)" ID="elementID10077" Root="تصوير برداري" Relation="cr-2" />
    <Tag Type="Target(M)" ID="elementID10080" Root="رينگ زوم" Relation="cr-2" />
    <Tag Type="Target(M)" ID="elementID10083" Root="نورگيري" Relation="cr-2" />
    <Tag Type="Target(M)" ID="elementID10086" Root="تصوير" Relation="cr-2" />
    <Tag Type="Target(M)" ID="elementID10089" Root="ارزش" Relation="cr-2" />
    <Tag Type="Target(M)" ID="elementID10092" Root="سنسور" Relation="cr-3" />
    <Tag Type="Target(M)" ID="elementID10095" Root="دوربين" Relation="cr-3" />
    <Tag Type="Target(I)" ID="tagID1001" Coordinate="[rev-1,132,137]" Relation="elementID1000" Value="" />
    <Tag Type="Opinion" ID="tagID1002" Coordinate="[rev-1,118,131]" Relation="tagID1001" Value="+" />
    <Tag Type="Target(I)" ID="tagID1004" Coordinate="[rev-4,35,43]" Relation="elementID1003" Value="" />
    <Tag Type="Opinion" ID="tagID1005" Coordinate="[rev-4,58,72]" Relation="tagID1004" Value="+" />
    <Tag Type="Target(I)" ID="tagID1007" Coordinate="[rev-22,19,34]" Relation="elementID1006" Value="" />
    <Tag Type="Opinion" ID="tagID1008" Coordinate="[rev-22,35,49]" Relation="tagID1007" Value="+" />
    <Tag Type="Target(I)" ID="tagID10010" Coordinate="[rev-23,0,7]" Relation="elementID1009" Value="" />
    <Tag Type="Opinion" ID="tagID10011" Coordinate="[rev-23,16,30]" Relation="tagID10010" Value="+" />
    <Tag Type="Target(I)" ID="tagID10013" Coordinate="[gr-1-1,0,7]" Relation="elementID10012" Value="" />
    <Tag Type="Opinion" ID="tagID10014" Coordinate="[gr-1-1,8,13]" Relation="tagID10013" Value="+" />
    <Tag Type="Target(I)" ID="tagID10016" Coordinate="[gr-2-4,6,18]" Relation="elementID10015" Value="" />
    <Tag Type="Opinion" ID="tagID10017" Coordinate="[gr-2-4,25,34]" Relation="tagID10016" Value="-" />
    <Tag Type="Target(I)" ID="tagID10019" Coordinate="[gr-2-4,93,101]" Relation="elementID10018" Value="" />
    <Tag Type="Opinion" ID="tagID10020" Coordinate="[gr-2-4,84,87]" Relation="tagID10019" Value="-" />
    <Tag Type="Target(I)" ID="tagID10022" Coordinate="[gr-2-5,6,13]" Relation="elementID10021" Value="" />
    <Tag Type="Opinion" ID="tagID10023" Coordinate="[gr-2-5,17,25]" Relation="tagID10022" Value="-" />
    <Tag Type="Target(I)" ID="tagID10025" Coordinate="[gr-2-5,48,53]" Relation="elementID10024" Value="" />
    <Tag Type="Opinion" ID="tagID10026" Coordinate="[gr-2-5,54,68]" Relation="tagID10025" Value="-" />
    <Tag Type="Target(I)" ID="tagID10028" Coordinate="[gr-2-8,74,78]" Relation="elementID10027" Value="" />
    <Tag Type="Opinion" ID="tagID10029" Coordinate="[gr-2-8,91,96]" Relation="tagID10028" Value="-" />
    <Tag Type="Target(I)" ID="tagID10031" Coordinate="[gr-3-2,38,42]" Relation="elementID10030" Value="" />
    <Tag Type="Opinion" ID="tagID10032" Coordinate="[gr-3-2,67,75]" Relation="tagID10031" Value="-" />
    <Tag Type="Target(I)" ID="tagID10034" Coordinate="[gr-4-1,6,12]" Relation="elementID10033" Value="" />
    <Tag Type="Opinion" ID="tagID10035" Coordinate="[gr-4-1,13,17]" Relation="tagID10034" Value="+" />
    <Tag Type="Target(I)" ID="tagID10037" Coordinate="[gr-5-1,57,67]" Relation="elementID10036" Value="" />
    <Tag Type="Opinion" ID="tagID10038" Coordinate="[gr-5-1,7,15]" Relation="tagID10037" Value="+" />
    <Tag Type="Opinion" ID="tagID10039" Coordinate="[gr-5-1,18,30]" Relation="tagID10037" Value="+" />
    <Tag Type="Opinion" ID="tagID10040" Coordinate="[gr-5-1,47,56]" Relation="tagID10037" Value="+" />
    <Tag Type="Target(I)" ID="tagID10042" Coordinate="[gr-6-2,83,93]" Relation="elementID10041" Value="" />
    <Tag Type="Opinion" ID="tagID10043" Coordinate="[gr-6-2,94,104]" Relation="tagID10042" Value="+" />
    <Tag Type="Target(I)" ID="tagID10050" Coordinate="[gr-6-14,83,88]" Relation="elementID10041" Value="" />
    <Tag Type="Opinion" ID="tagID10051" Coordinate="[gr-6-14,89,93]" Relation="tagID10050" Value="+" />
    <Tag Type="Target(I)" ID="tagID10045" Coordinate="[gr-6-10,22,31]" Relation="elementID10044" Value="" />
    <Tag Type="Opinion" ID="tagID10046" Coordinate="[gr-6-10,32,45]" Relation="tagID10045" Value="+" />
    <Tag Type="Target(I)" ID="tagID10048" Coordinate="[gr-6-12,31,36]" Relation="elementID10047" Value="" />
    <Tag Type="Opinion" ID="tagID10049" Coordinate="[gr-6-12,27,30]" Relation="tagID10048" Value="+" />
    <Tag Type="Target(I)" ID="tagID10053" Coordinate="[cr-3-1,77,84]" Relation="elementID10052" Value="" />
    <Tag Type="Opinion" ID="tagID10054" Coordinate="[cr-3-1,85,95]" Relation="tagID10053" Value="+" />
    <Tag Type="Target(I)" ID="tagID10056" Coordinate="[cr-3-1,124,127]" Relation="elementID10055" Value="" />
    <Tag Type="Opinion" ID="tagID10057" Coordinate="[cr-3-1,134,136]" Relation="tagID10056" Value="+" />
    <Tag Type="Target(I)" ID="tagID10059" Coordinate="[cr-3-1,130,133]" Relation="elementID10058" Value="" />
    <Tag Type="Opinion" ID="tagID10060" Coordinate="[cr-3-1,134,136]" Relation="tagID10059" Value="+" />
    <Tag Type="Target(I)" ID="tagID10062" Coordinate="[cr-5-1,13,19]" Relation="elementID10061" Value="" />
    <Tag Type="Opinion" ID="tagID10063" Coordinate="[cr-5-1,0,12]" Relation="tagID10062" Value="+" />
    <Tag Type="Target(I)" ID="tagID10065" Coordinate="[cr-5-1,58,63]" Relation="elementID10064" Value="" />
    <Tag Type="Opinion" ID="tagID10066" Coordinate="[cr-5-1,64,86]" Relation="tagID10065" Value="+" />
    <Tag Type="Target(I)" ID="tagID10068" Coordinate="[cr-6-1,32,38]" Relation="elementID10067" Value="" />
    <Tag Type="Opinion" ID="tagID10069" Coordinate="[cr-6-1,39,50]" Relation="tagID10068" Value="+" />
    <Tag Type="Opinion" ID="tagID10070" Coordinate="[cr-6-1,53,62]" Relation="tagID10068" Value="+" />
    <Tag Type="Target(I)" ID="tagID10072" Coordinate="[cr-6-1,69,75]" Relation="elementID10071" Value="" />
    <Tag Type="Opinion" ID="tagID10073" Coordinate="[cr-6-1,76,81]" Relation="tagID10072" Value="+" />
    <Tag Type="Target(I)" ID="tagID10075" Coordinate="[cr-6-1,171,176]" Relation="elementID10074" Value="" />
    <Tag Type="Opinion" ID="tagID10076" Coordinate="[cr-6-1,177,182]" Relation="tagID10075" Value="+" />
    <Tag Type="Target(I)" ID="tagID10078" Coordinate="[cr-2-4,6,18]" Relation="elementID10077" Value="" />
    <Tag Type="Opinion" ID="tagID10079" Coordinate="[cr-2-4,25,34]" Relation="tagID10078" Value="-" />
    <Tag Type="Target(I)" ID="tagID10081" Coordinate="[cr-2-4,93,101]" Relation="elementID10080" Value="" />
    <Tag Type="Opinion" ID="tagID10082" Coordinate="[cr-2-4,84,87]" Relation="tagID10081" Value="-" />
    <Tag Type="Target(I)" ID="tagID10084" Coordinate="[cr-2-5,6,13]" Relation="elementID10083" Value="" />
    <Tag Type="Opinion" ID="tagID10085" Coordinate="[cr-2-5,17,25]" Relation="tagID10084" Value="-" />
    <Tag Type="Target(I)" ID="tagID10087" Coordinate="[cr-2-5,47,52]" Relation="elementID10086" Value="" />
    <Tag Type="Opinion" ID="tagID10088" Coordinate="[cr-2-5,53,67]" Relation="tagID10087" Value="-" />
    <Tag Type="Target(I)" ID="tagID10090" Coordinate="[cr-2-8,75,79]" Relation="elementID10089" Value="" />
    <Tag Type="Opinion" ID="tagID10091" Coordinate="[cr-2-8,92,97]" Relation="tagID10090" Value="-" />
    <Tag Type="Target(I)" ID="tagID10093" Coordinate="[cr-3-1,59,64]" Relation="elementID10092" Value="" />
    <Tag Type="Opinion" ID="tagID10094" Coordinate="[cr-3-1,70,74]" Relation="tagID10093" Value="" />
    <Tag Type="Target(I)" ID="tagID10096" Coordinate="[cr-3-1,145,151]" Relation="elementID10095" Value="" />
    <Tag Type="Opinion" ID="tagID10097" Coordinate="[cr-3-1,159,166]" Relation="tagID10096" Value="+" />
  </Tags>
  <Keywords>
    <Keyword ID="keywordID1000" Coordinate="[rev-1,118,131]" Value="+" />
    <Keyword ID="keywordID1001" Coordinate="[rev-4,12,15]" Value="+" />
    <Keyword ID="keywordID1002" Coordinate="[rev-4,58,72]" Value="+" />
    <Keyword ID="keywordID1003" Coordinate="[rev-5,15,25]" Value="+" />
    <Keyword ID="keywordID1004" Coordinate="[rev-7,83,87]" Value="+" />
    <Keyword ID="keywordID1005" Coordinate="[rev-7,88,94]" Value="+" />
    <Keyword ID="keywordID1006" Coordinate="[rev-11,60,72]" Value="+" />
    <Keyword ID="keywordID1007" Coordinate="[rev-12,17,27]" Value="+" />
    <Keyword ID="keywordID1008" Coordinate="[rev-13,14,21]" Value="+" />
    <Keyword ID="keywordID1009" Coordinate="[rev-13,7,13]" Value="+" />
    <Keyword ID="keywordID10010" Coordinate="[rev-13,53,57]" Value="+" />
    <Keyword ID="keywordID10011" Coordinate="[rev-14,71,78]" Value="+" />
    <Keyword ID="keywordID10012" Coordinate="[rev-14,79,83]" Value="+" />
    <Keyword ID="keywordID10013" Coordinate="[rev-15,37,47]" Value="+" />
    <Keyword ID="keywordID10014" Coordinate="[rev-15,48,56]" Value="-" />
    <Keyword ID="keywordID10017" Coordinate="[rev-22,35,49]" Value="+" />
    <Keyword ID="keywordID10018" Coordinate="[rev-23,16,30]" Value="+" />
    <Keyword ID="keywordID10019" Coordinate="[rev-24,22,27]" Value="-" />
    <Keyword ID="keywordID10020" Coordinate="[rev-26,81,89]" Value="+" />
    <Keyword ID="keywordID10021" Coordinate="[rev-26,90,96]" Value="+" />
    <Keyword ID="keywordID10022" Coordinate="[gr-1-1,8,13]" Value="+" />
    <Keyword ID="keywordID10023" Coordinate="[gr-2-2,0,8]" Value="-" />
    <Keyword ID="keywordID10024" Coordinate="[gr-2-2,40,43]" Value="-" />
    <Keyword ID="keywordID10025" Coordinate="[gr-2-3,66,69]" Value="-" />
    <Keyword ID="keywordID10026" Coordinate="[gr-2-4,25,34]" Value="-" />
    <Keyword ID="keywordID10027" Coordinate="[gr-2-4,50,56]" Value="-" />
    <Keyword ID="keywordID10028" Coordinate="[gr-2-4,84,87]" Value="-" />
    <Keyword ID="keywordID10029" Coordinate="[gr-2-4,187,191]" Value="-" />
    <Keyword ID="keywordID10030" Coordinate="[gr-2-5,17,25]" Value="-" />
    <Keyword ID="keywordID10031" Coordinate="[gr-2-5,54,68]" Value="-" />
    <Keyword ID="keywordID10032" Coordinate="[gr-2-7,119,123]" Value="-" />
    <Keyword ID="keywordID10033" Coordinate="[gr-2-7,170,174]" Value="-" />
    <Keyword ID="keywordID10034" Coordinate="[gr-2-7,95,102]" Value="-" />
    <Keyword ID="keywordID10035" Coordinate="[gr-2-8,91,96]" Value="-" />
    <Keyword ID="keywordID10036" Coordinate="[gr-3-2,67,75]" Value="-" />
    <Keyword ID="keywordID10037" Coordinate="[gr-4-1,13,17]" Value="+" />
    <Keyword ID="keywordID10051" Coordinate="[cr-3-1,7,14]" Value="+" />
    <Keyword ID="keywordID10039" Coordinate="[gr-5-1,7,15]" Value="+" />
    <Keyword ID="keywordID10040" Coordinate="[gr-5-1,18,30]" Value="+" />
    <Keyword ID="keywordID10042" Coordinate="[gr-5-1,47,56]" Value="+" />
    <Keyword ID="keywordID10043" Coordinate="[gr-6-2,94,104]" Value="+" />
    <Keyword ID="keywordID10044" Coordinate="[gr-6-2,43,48]" Value="+" />
    <Keyword ID="keywordID10045" Coordinate="[gr-6-5,62,66]" Value="+" />
    <Keyword ID="keywordID10046" Coordinate="[gr-6-5,14,22]" Value="+" />
    <Keyword ID="keywordID10047" Coordinate="[gr-6-10,6,10]" Value="+" />
    <Keyword ID="keywordID10048" Coordinate="[gr-6-10,32,45]" Value="+" />
    <Keyword ID="keywordID10049" Coordinate="[gr-6-12,27,30]" Value="+" />
    <Keyword ID="keywordID10050" Coordinate="[gr-6-14,89,93]" Value="+" />
    <Keyword ID="keywordID10052" Coordinate="[cr-3-1,0,6]" Value="" />
    <Keyword ID="keywordID10053" Coordinate="[cr-3-1,70,74]" Value="" />
    <Keyword ID="keywordID10054" Coordinate="[cr-3-1,85,95]" Value="+" />
    <Keyword ID="keywordID10055" Coordinate="[cr-3-1,134,136]" Value="+" />
    <Keyword ID="keywordID10056" Coordinate="[cr-3-1,134,136]" Value="+" />
    <Keyword ID="keywordID10057" Coordinate="[cr-4-1,70,76]" Value="+" />
    <Keyword ID="keywordID10058" Coordinate="[cr-4-1,164,173]" Value="+" />
    <Keyword ID="keywordID10059" Coordinate="[cr-5-1,0,12]" Value="+" />
    <Keyword ID="keywordID10060" Coordinate="[cr-5-1,64,86]" Value="+" />
    <Keyword ID="keywordID10061" Coordinate="[cr-6-1,39,50]" Value="+" />
    <Keyword ID="keywordID10062" Coordinate="[cr-6-1,53,62]" Value="+" />
    <Keyword ID="keywordID10063" Coordinate="[cr-6-1,76,81]" Value="+" />
    <Keyword ID="keywordID10064" Coordinate="[cr-6-1,161,164]" Value="+" />
    <Keyword ID="keywordID10065" Coordinate="[cr-6-1,177,182]" Value="+" />
    <Keyword ID="keywordID10066" Coordinate="[cr-6-1,191,195]" Value="+" />
    <Keyword ID="keywordID10067" Coordinate="[cr-6-1,251,257]" Value="" />
    <Keyword ID="keywordID10068" Coordinate="[cr-7-1,0,8]" Value="+" />
    <Keyword ID="keywordID10069" Coordinate="[cr-7-1,11,23]" Value="+" />
    <Keyword ID="keywordID10070" Coordinate="[cr-7-1,26,35]" Value="+" />
    <Keyword ID="keywordID10071" Coordinate="[cr-7-1,38,47]" Value="+" />
    <Keyword ID="keywordID10072" Coordinate="[rev-5,7,14]" Value="+" />
    <Keyword ID="keywordID10073" Coordinate="[rev-8,75,80]" Value="" />
    <Keyword ID="keywordID10074" Coordinate="[rev-24,28,31]" Value="" />
    <Keyword ID="keywordID10075" Coordinate="[rev-30,84,91]" Value="" />
    <Keyword ID="keywordID10076" Coordinate="[cr-2-2,0,8]" Value="-" />
    <Keyword ID="keywordID10077" Coordinate="[cr-2-2,40,43]" Value="-" />
    <Keyword ID="keywordID10078" Coordinate="[cr-2-3,66,69]" Value="-" />
    <Keyword ID="keywordID10079" Coordinate="[cr-2-4,25,34]" Value="-" />
    <Keyword ID="keywordID10080" Coordinate="[cr-2-4,84,87]" Value="-" />
    <Keyword ID="keywordID10081" Coordinate="[cr-2-4,187,191]" Value="-" />
    <Keyword ID="keywordID10082" Coordinate="[cr-2-5,17,25]" Value="-" />
    <Keyword ID="keywordID10083" Coordinate="[cr-2-5,53,67]" Value="-" />
    <Keyword ID="keywordID10084" Coordinate="[cr-2-7,95,102]" Value="-" />
    <Keyword ID="keywordID10085" Coordinate="[cr-2-7,119,123]" Value="-" />
    <Keyword ID="keywordID10086" Coordinate="[cr-2-7,170,174]" Value="-" />
    <Keyword ID="keywordID10087" Coordinate="[cr-2-8,92,97]" Value="-" />
    <Keyword ID="keywordID10088" Coordinate="[cr-3-1,159,166]" Value="+" />
    <Keyword ID="keywordID10089" Coordinate="[cr-4-2,3,7]" Value="+" />
  </Keywords>
  <Index>
    <Keyword_Index Value="90" />
    <Tag_Index Value="98" />
  </Index>
</Product>